cleanlang/__init__.py
cleanlang/extras.py
cleanlang-3.3.dist-info/METADATA
cleanlang-3.3.dist-info/WHEEL
cleanlang-3.3.dist-info/licenses/LICENSE
cleanlang-3.3.dist-info/RECORD
