Metadata-Version: 2.4
Name: cleanlang
Version: 3.3
Summary: A module used to filter out profane and/or offensive language of your choosing!
Project-URL: Repository, https://github.com/AnniePrograms/cleanlang
Project-URL: BugTracker, https://github.com/AnniePrograms/cleanlang/issues
Author-email: Annie <SocializingAnnie@gmail.com>
License: MIT
License-File: LICENSE
Requires-Python: >=3.8
Requires-Dist: fuzzywuzzy[speedup]
